pmx/AbsRestraints.py
pmx/__init__.py
pmx/_pmx.cpython-37m-darwin.so
pmx/_version.py
pmx/_xdrio.cpython-37m-darwin.so
pmx/alchemy.py
pmx/analysis.py
pmx/atom.py
pmx/atomselection.py
pmx/builder.py
pmx/chain.py
pmx/estimators.py
pmx/ffparser.py
pmx/forcefield.py
pmx/geometry.py
pmx/gmx.py
pmx/jobscript.py
pmx/library.py
pmx/ligand_alchemy.py
pmx/model.py
pmx/molecule.py
pmx/mutdb.py
pmx/ndx.py
pmx/options.py
pmx/parser.py
pmx/rosetta.py
pmx/rosetta_analyze.py
pmx/rotamer.py
pmx/summary.py
pmx/utils.py
pmx/xdrfile.py
pmx/xtc.py
pmx/data/aminoacids.pkl
pmx/data/bbdep.pkl
pmx/data/blosum62_new.mat
pmx/data/bp.pkl
pmx/data/bp_amber.pkl
pmx/data/bp_charmm.pkl
pmx/data/rna.pkl
pmx/data/mutff/atommass.dat
pmx/data/mutff/elements.dat
pmx/data/mutff/residuetypes.dat
pmx/data/mutff/spc216.gro
pmx/data/mutff/specbond.dat
pmx/data/mutff/vdwradii.dat
pmx/data/mutff/xlateat.dat
pmx/data/mutff/amber14sbmut.ff/Makefile.am
pmx/data/mutff/amber14sbmut.ff/Makefile.in
pmx/data/mutff/amber14sbmut.ff/aminoacids.arn
pmx/data/mutff/amber14sbmut.ff/aminoacids.c.tdb
pmx/data/mutff/amber14sbmut.ff/aminoacids.hdb
pmx/data/mutff/amber14sbmut.ff/aminoacids.n.tdb
pmx/data/mutff/amber14sbmut.ff/aminoacids.r2b
pmx/data/mutff/amber14sbmut.ff/aminoacids.rtp
pmx/data/mutff/amber14sbmut.ff/aminoacids.vsd
pmx/data/mutff/amber14sbmut.ff/atomtypes.atp
pmx/data/mutff/amber14sbmut.ff/dna.arn
pmx/data/mutff/amber14sbmut.ff/dna.hdb
pmx/data/mutff/amber14sbmut.ff/dna.r2b
pmx/data/mutff/amber14sbmut.ff/dna.rtp
pmx/data/mutff/amber14sbmut.ff/ffbonded.itp
pmx/data/mutff/amber14sbmut.ff/ffnonbonded.itp
pmx/data/mutff/amber14sbmut.ff/forcefield.doc
pmx/data/mutff/amber14sbmut.ff/forcefield.itp
pmx/data/mutff/amber14sbmut.ff/gbsa.itp
pmx/data/mutff/amber14sbmut.ff/ions.itp
pmx/data/mutff/amber14sbmut.ff/mutres.mtp
pmx/data/mutff/amber14sbmut.ff/mutres.rtp
pmx/data/mutff/amber14sbmut.ff/rna.arn
pmx/data/mutff/amber14sbmut.ff/rna.hdb
pmx/data/mutff/amber14sbmut.ff/rna.r2b
pmx/data/mutff/amber14sbmut.ff/rna.rtp
pmx_biobb-4.1.3.dist-info/LICENSE
pmx_biobb-4.1.3.dist-info/METADATA
pmx_biobb-4.1.3.dist-info/WHEEL
pmx_biobb-4.1.3.dist-info/entry_points.txt
pmx_biobb-4.1.3.dist-info/top_level.txt
pmx_biobb-4.1.3.dist-info/RECORD
