Metadata-Version: 2.1
Name: pmx-biobb
Version: 4.1.3
Summary: Toolkit for free-energy calculation setup/analysis and biomolecular structure handling
Home-page: https://github.com/deGrootLab/pmx/tree/develop
Author: Daniel Seeliger, Vytautas Gapsys
Author-email: d.seeliger@gmx.net, vytautas.gapsys@gmail.com
License: LGPL-3.0
Platform: UNKNOWN
Classifier: Programming Language :: Python
Classifier: Intended Audience :: Science/Research
Classifier: Topic :: Scientific/Engineering
Requires-Python: >=3.7
License-File: LICENSE
Requires-Dist: numpy
Requires-Dist: scipy
Requires-Dist: matplotlib
Requires-Dist: rdkit
